web3author/__init__.py
web3author/web3author.py
web3author-1.0.0.dist-info/METADATA
web3author-1.0.0.dist-info/WHEEL
web3author-1.0.0.dist-info/top_level.txt
web3author-1.0.0.dist-info/RECORD
