Metadata-Version: 2.1
Name: web3author
Version: 1.0.0
Summary: tools for web3
Home-page: 
Author: web3rpcs
Author-email: 
Classifier: Programming Language :: Python :: 3
Classifier: License :: OSI Approved :: MIT License
Classifier: Operating System :: OS Independent
Requires-Python: >=3.6
